skt-war-result/__init__.py
skt-war-result/__main__.py
sktwar/__init__.py
sktwar/main.py
skt_war_result-1.0.3.dist-info/LICENSE.md
skt_war_result-1.0.3.dist-info/METADATA
skt_war_result-1.0.3.dist-info/WHEEL
skt_war_result-1.0.3.dist-info/entry_points.txt
skt_war_result-1.0.3.dist-info/top_level.txt
skt_war_result-1.0.3.dist-info/RECORD
