Metadata-Version: 2.1
Name: skt-war-result
Version: 1.0.3
Summary: Lists war results for Japanese servers in Lineage Mobile game.
Home-page: https://github.com/yumenoshima/skt-war-result
Author: yumenoshima
Author-email: skt.tofuya@gmail.com
License: BSD
Download-URL: https://github.com/yumenoshima/skt-war-result/tarball/1.0.3
Platform: UNKNOWN
Classifier: Development Status :: 3 - Alpha
Classifier: Intended Audience :: Developers
Classifier: Programming Language :: Python :: 3
Requires-Dist: sphinx
Requires-Dist: sphinx-rtd-theme
Requires-Dist: nose
Requires-Dist: coverage
Requires-Dist: pypi-publisher
Requires-Dist: lxml
